switch_win/__init__.py
switch_win/back.py
switch_win/main.py
switch_win-2024.2.8.5.dist-info/LICENSE
switch_win-2024.2.8.5.dist-info/METADATA
switch_win-2024.2.8.5.dist-info/WHEEL
switch_win-2024.2.8.5.dist-info/entry_points.txt
switch_win-2024.2.8.5.dist-info/top_level.txt
switch_win-2024.2.8.5.dist-info/RECORD
