Metadata-Version: 2.1
Name: switch_win
Version: 2024.2.8.5
Summary: 确定的切换窗口
Home-page: https://github.com/yanchengxin2018/qui
Author: YanChengxin
Author-email: yan.cheng.xin@foxmail.com
Project-URL: Bug Tracker, https://github.com/yanchengxin2018/switch_win
Classifier: Programming Language :: Python :: 3
Classifier: License :: OSI Approved :: MIT License
Classifier: Operating System :: OS Independent
Requires-Python: >=3.10.12
License-File: LICENSE
Requires-Dist: keyboard
Requires-Dist: python-xlib
